{
  "title": "Le sourire des sons",
  "collect": "Merci de renseigner les informations suivantes :",
  "collectButton": "Valider",
  "introduction": "Dans cette expérience, vous allez entendre des exemples de prononciations du son /a/, et nous vous demandons de juger s'ils expriment plutôt le sourire ou l'interrogation",
  "pause": "Nous vous proposons une pause de quelques secondes",
  "pauseOver": "La pause est terminée, vous pouvez reprendre l'expérience",
  "resume": "Reprise de l'expérience",
  "end": "Fin de l'expérience",
  "thanks": "Merci pour votre participation",
  "closed": "Expérience déjà effectuée par ce·tte participant·e",
  "playSounds": "écoute extrait",
  "next": "pour continuer",
  "space": "espace",
  "question": "Cet extrait exprime plutôt :",
  "keyAlt1": "f",
  "keyAlt2": "j",
  "labelAlt1": "le sourire",
  "labelAlt2": "l'étonnement",
  "codeAlt1": "smile",
  "codeAlt2": "astonishment"
}